{"cameraMode":{"drawMode":0,"name":"Shaded","section":"Shading Mode"},"sceneLighting":true,"audioPlay":false,"sceneViewState":{"showFog":true,"showMaterialUpdate":false,"showSkybox":true,"showFlares":true,"showImageEffects":true,"showParticleSystems":true},"in2DMode":false,"pivot":{"x":24.511137008666993,"y":26.952333450317384,"z":92.54461669921875},"rotation":{"x":0.15121109783649445,"y":0.32586148381233218,"z":-0.052706725895404819,"w":0.9318989515304565},"size":53.598358154296878,"orthographic":false}